{
  "timestamp": "2025-11-08T14:27:35+00:00",
  "appUrl": "http://localhost:3000",
  "checks": [
    {
      "name": "root_page",
      "status": "PASS",
      "httpCode": 200,
      "correlationId": null,
      "durationMs": 0,
      "message": "HTML page served successfully"
    },
    {
      "name": "health_endpoint",
      "status": "PASS",
      "httpCode": 200,
      "correlationId": "req_1762612055102_a3xbyrtab",
      "durationMs": 0,
      "message": "Liveness check passed"
    },
    {
      "name": "readiness_endpoint",
      "status": "PASS",
      "httpCode": 200,
      "correlationId": "req_1762612055209_581z7ytmg",
      "durationMs": 0,
      "message": "Readiness check passed, DB healthy"
    }
  ]
}